llama_index/llms/portkey/__init__.py
llama_index/llms/portkey/base.py
llama_index/llms/portkey/utils.py
llama_index_llms_portkey-0.4.2.dist-info/METADATA
llama_index_llms_portkey-0.4.2.dist-info/WHEEL
llama_index_llms_portkey-0.4.2.dist-info/licenses/LICENSE
llama_index_llms_portkey-0.4.2.dist-info/RECORD
