Metadata-Version: 2.4
Name: llama-index-llms-portkey
Version: 0.4.2
Summary: llama-index llms portkey integration
Author-email: Your Name <you@example.com>
License-Expression: MIT
License-File: LICENSE
Requires-Python: <4.0,>=3.9
Requires-Dist: llama-index-core<0.15,>=0.14.3
Requires-Dist: llama-index-llms-anthropic<0.9,>=0.8.0
Requires-Dist: llama-index-llms-openai<0.7,>=0.6.0
Requires-Dist: portkey-ai<2,>=1.1.4
Requires-Dist: portkey<0.2,>=0.1.2
